mlops_agent/__init__.py
mlops_agent-0.1.0.dist-info/METADATA
mlops_agent-0.1.0.dist-info/WHEEL
mlops_agent-0.1.0.dist-info/RECORD
